{"lP7kJHVygW/YekEvT2XR0w==":"mbr-1920x1058.jpg","bJQp5hs8ui31hex4jK7NBw==":"team-1000x667.jpg","fVquXtKRCblqpBuM8s/4Wg==":"10615959_826966964029743_6219585656257770696_n-1-653x960.jpg","0btIWR3EYsCzBBZ1CeWrWg==":"img-43-2000x1333.jpg","l1tYJnKfw/18OIvlTpnnaA==":"img-43-1000x667.jpg","wU2r5/LUkcxSsQLgRJHbmg==":"20190308-60027-510x365.jpg","8PHaNBoqeLvZSNYMReRNXQ==":"1-500x500.jpg","mqpGfA1y2UqpSghivLvBoA==":"2-500x500.jpg","HNbnJ4uTNbNLrEJdbBLAYw==":"varun-sunil-(2)-500x500.jpg","w/DgzeY4+WXXLQ71Vy1oQA==":"%D0%BD%D0%B5%D1%82-%D0%B0%D0%B2%D0%B0%D1%82%D0%B0%D1%80%D0%B0-png-2-300x300.png","jsvluF4a0Fn1KP6BDxJCgg==":"hero%20(1)-400x604.jpg","lFpn6fG8GFRpXs4ZPutuoA==":"heroine-(4)-400x344.jpg","nO8ELt6EWnlmM4co3tCrYA==":"hero%20father%20(2)-400x401.jpg","EBVnelYt6kEnLxZ9HuJtZQ==":"hero-frendd-1-400x400.jpg","c63BOTYpXhrmR5HA8jjV7Q==":"hero%20mother-400x400.jpg","+W8YNB245U7L1GIsQFiBhg==":"heroine-(4)-1-400x344.jpg","bSXOednmwT1YxLc4+uklKw==":"abhiyum%20naanum%20-%202nd%20short%20film%20poster-684x1000.jpg","c0F/R5tKZZDMNvkAeGDaaw==":"eenadu%20velugu%20paper%20article%20about%20short%20film%20#shubham-1054x2395.jpg","1Rvlue3BkvFLDkoQAobzFg==":"not%20permanent%20-%20pilot%20poster-675x1000.jpg","YDrq3qcOn38hP9aqncKh7Q==":"not%20permanent%201st%20shedule%20-%20working%20still%20as%20a%20director-1000x667.jpg","MYCIxBT0IdwDPeJJMpZddg==":"not%20permanent%20climax%20song%20recording-1000x667.jpg","Qy9ZvFIFZrQ9r/wOrFZPeA==":"not%20permanent%20demo%20working%20still%20as%20a%20director-1000x635.jpg","OXNWpEnjrGK1rYzl/Kzu5g==":"short%20film%20%20making%20stills%20(1)-960x640.jpg","NEgbvFljXpr5X7j342O/nQ==":"short%20film%20%20making%20stills%20(2)-720x518.jpg","jxI21KJ6nmja2G2mYdPSmg==":"shubham%20(%202nd%20short%20film%20di%20work%20in%20chennai%20-%20prism%20&%20pixals%20studio%20)-960x720.jpg","dAoQIw0ozhfCEzwElQCXxA==":"shubham%20short%20film%20poster%20launch%20with%20odia%20super%20star%20#anubhav%20mohanty%20(%20member%20of%20parliment%20)-1000x667.jpg","Q0av1+zTxCh95KHuSnYA3g==":"img-30-1000x667.jpg","beMYe7UAg+eV8r9ebe4CnA==":"img-31-1000x667.jpg","Uu71JR4qSJyl3zS5cT1pOw==":"img-44-1000x667.jpg","iz0SvzIu4rNTpKXPbfpX2Q==":"img-9988-1000x667.jpg","nYRJeAYvfl8Q0J9NMx/5bQ==":"img-9935-1000x667.jpg","a+kXb30DfIR2gflDYIZong==":"img-163-1000x667.jpg","ADcSII7jJJlS/xra0c9TuQ==":"img_20180903-61453-750x1000.jpg","787gnIiUQ1pbTFTV/C2AJg==":"locations%20visit%20-%20ground%20work%20for%20shoot%20(1)-1000x750.jpg","TXeXstKePubNHgCGkyHRNQ==":"locations%20visit%20-%20ground%20work%20for%20shoot%20(2)-1000x750.jpg","afOmB2EbcJdrlGhOK/ox+g==":"not%20permanent%20-%201st%20shedule%20making%20stills%20(1)-1000x750.jpg","6v2zWzxlnemPbmcSnRkiCg==":"not%20permanent%20-%201st%20shedule%20making%20stills%20(2)-1000x750.jpg","OCR1+cR1dmchJWTgPaJ46g==":"play%20tm%20-%20a%20youtube%20channel-1040x585.jpg","bcwC6HZouKiG96FD1wh8pA==":"play%20tm%201%20lack%20subscribers%20celebrations-1000x598.jpg","obi2gl1g07/kiwF1h5kLCQ==":"not%20permanent%20-%20pilot%20poster-675x1000.jpg","dxeAB8PSUTqQ8dfm9XI5Jg==":"lecturer%20(1)-400x339.jpg"}